README.txt
buildout.cfg
setup.py
src/zc/__init__.py
src/zc.demostorage2.egg-info/PKG-INFO
src/zc.demostorage2.egg-info/SOURCES.txt
src/zc.demostorage2.egg-info/dependency_links.txt
src/zc.demostorage2.egg-info/namespace_packages.txt
src/zc.demostorage2.egg-info/not-zip-safe
src/zc.demostorage2.egg-info/requires.txt
src/zc.demostorage2.egg-info/top_level.txt
src/zc/demostorage2/README.txt
src/zc/demostorage2/__init__.py
src/zc/demostorage2/component.xml
src/zc/demostorage2/synchronized.py
src/zc/demostorage2/synchronized.txt
src/zc/demostorage2/tests.py