Metadata-Version: 1.0
Name: zc.demostorage2
Version: 0.1.3
Summary: ZODB storage that stores changes relative to a base storage
Home-page: UNKNOWN
Author: Jim Fulton
Author-email: jim@zope.com
License: ZPL 2.1
Platform: UNKNOWN
Classifier: Intended Audience :: Developers
Classifier: License :: OSI Approved :: Zope Public License
Classifier: Framework :: ZODB
